scaling/__init__.py
scaling/scaling.py
scaling-0.2.3.dist-info/METADATA
scaling-0.2.3.dist-info/RECORD
scaling-0.2.3.dist-info/WHEEL
scaling-0.2.3.dist-info/top_level.txt
